{
  "165": {
    "name": "ledyba",
    "top_moves": [
      {
        "move": "focus-punch",
        "type": "fighting",
        "power": 150,
        "score": 115.0
      },
      {
        "move": "solar-beam",
        "type": "grass",
        "power": 120,
        "score": 109.0
      },
      {
        "move": "bug-buzz",
        "type": "bug",
        "power": 90,
        "score": 103.0
      },
      {
        "move": "double-edge",
        "type": "normal",
        "power": 120,
        "score": 94.0
      },
      {
        "move": "air-slash",
        "type": "flying",
        "power": 75,
        "score": 92.0
      },
      {
        "move": "u-turn",
        "type": "bug",
        "power": 70,
        "score": 89.0
      },
      {
        "move": "silver-wind",
        "type": "bug",
        "power": 60,
        "score": 82.0
      }
    ]
  },
  "166": {
    "name": "ledian",
    "top_moves": [
      {
        "move": "hyper-beam",
        "type": "normal",
        "power": 150,
        "score": 129.0
      },
      {
        "move": "giga-impact",
        "type": "normal",
        "power": 150,
        "score": 129.0
      },
      {
        "move": "focus-punch",
        "type": "fighting",
        "power": 150,
        "score": 115.0
      },
      {
        "move": "solar-beam",
        "type": "grass",
        "power": 120,
        "score": 109.0
      },
      {
        "move": "bug-buzz",
        "type": "bug",
        "power": 90,
        "score": 103.0
      },
      {
        "move": "double-edge",
        "type": "normal",
        "power": 120,
        "score": 94.0
      },
      {
        "move": "air-slash",
        "type": "flying",
        "power": 75,
        "score": 92.0
      }
    ]
  },
  "167": {
    "name": "spinarak",
    "top_moves": [
      {
        "move": "megahorn",
        "type": "bug",
        "power": 120,
        "score": 122.5
      },
      {
        "move": "solar-beam",
        "type": "grass",
        "power": 120,
        "score": 109.0
      },
      {
        "move": "sludge-wave",
        "type": "poison",
        "power": 95,
        "score": 106.5
      },
      {
        "move": "sludge-bomb",
        "type": "poison",
        "power": 90,
        "score": 103.0
      },
      {
        "move": "bug-buzz",
        "type": "bug",
        "power": 90,
        "score": 103.0
      },
      {
        "move": "leech-life",
        "type": "bug",
        "power": 80,
        "score": 96.0
      },
      {
        "move": "poison-jab",
        "type": "poison",
        "power": 80,
        "score": 96.0
      }
    ]
  },
  "168": {
    "name": "ariados",
    "top_moves": [
      {
        "move": "hyper-beam",
        "type": "normal",
        "power": 150,
        "score": 129.0
      },
      {
        "move": "giga-impact",
        "type": "normal",
        "power": 150,
        "score": 129.0
      },
      {
        "move": "megahorn",
        "type": "bug",
        "power": 120,
        "score": 122.5
      },
      {
        "move": "solar-beam",
        "type": "grass",
        "power": 120,
        "score": 109.0
      },
      {
        "move": "sludge-wave",
        "type": "poison",
        "power": 95,
        "score": 106.5
      },
      {
        "move": "sludge-bomb",
        "type": "poison",
        "power": 90,
        "score": 103.0
      },
      {
        "move": "bug-buzz",
        "type": "bug",
        "power": 90,
        "score": 103.0
      }
    ]
  },
  "169": {
    "name": "crobat",
    "top_moves": [
      {
        "move": "sky-attack",
        "type": "flying",
        "power": 140,
        "score": 152.0
      },
      {
        "move": "hyper-beam",
        "type": "normal",
        "power": 150,
        "score": 129.0
      },
      {
        "move": "giga-impact",
        "type": "normal",
        "power": 150,
        "score": 129.0
      },
      {
        "move": "brave-bird",
        "type": "flying",
        "power": 120,
        "score": 124.0
      },
      {
        "move": "hurricane",
        "type": "flying",
        "power": 110,
        "score": 114.0
      },
      {
        "move": "sludge-bomb",
        "type": "poison",
        "power": 90,
        "score": 103.0
      },
      {
        "move": "fly",
        "type": "flying",
        "power": 90,
        "score": 102.5
      }
    ]
  },
  "170": {
    "name": "chinchou",
    "top_moves": [
      {
        "move": "zap-cannon",
        "type": "electric",
        "power": 120,
        "score": 119.0
      },
      {
        "move": "hydro-pump",
        "type": "water",
        "power": 110,
        "score": 115.0
      },
      {
        "move": "thunder",
        "type": "electric",
        "power": 110,
        "score": 114.0
      },
      {
        "move": "surf",
        "type": "water",
        "power": 90,
        "score": 103.0
      },
      {
        "move": "thunderbolt",
        "type": "electric",
        "power": 90,
        "score": 103.0
      },
      {
        "move": "wild-charge",
        "type": "electric",
        "power": 90,
        "score": 103.0
      },
      {
        "move": "muddy-water",
        "type": "water",
        "power": 90,
        "score": 101.5
      }
    ]
  },
  "171": {
    "name": "lanturn",
    "top_moves": [
      {
        "move": "hyper-beam",
        "type": "normal",
        "power": 150,
        "score": 129.0
      },
      {
        "move": "giga-impact",
        "type": "normal",
        "power": 150,
        "score": 129.0
      },
      {
        "move": "zap-cannon",
        "type": "electric",
        "power": 120,
        "score": 119.0
      },
      {
        "move": "hydro-pump",
        "type": "water",
        "power": 110,
        "score": 115.0
      },
      {
        "move": "thunder",
        "type": "electric",
        "power": 110,
        "score": 114.0
      },
      {
        "move": "surf",
        "type": "water",
        "power": 90,
        "score": 103.0
      },
      {
        "move": "thunderbolt",
        "type": "electric",
        "power": 90,
        "score": 103.0
      }
    ]
  },
  "172": {
    "name": "pichu",
    "top_moves": [
      {
        "move": "volt-tackle",
        "type": "electric",
        "power": 120,
        "score": 124.0
      },
      {
        "move": "zap-cannon",
        "type": "electric",
        "power": 120,
        "score": 119.0
      },
      {
        "move": "thunder",
        "type": "electric",
        "power": 110,
        "score": 114.0
      },
      {
        "move": "thunderbolt",
        "type": "electric",
        "power": 90,
        "score": 103.0
      },
      {
        "move": "wild-charge",
        "type": "electric",
        "power": 90,
        "score": 103.0
      },
      {
        "move": "double-edge",
        "type": "normal",
        "power": 120,
        "score": 94.0
      },
      {
        "move": "thunder-punch",
        "type": "electric",
        "power": 75,
        "score": 92.5
      }
    ]
  },
  "173": {
    "name": "cleffa",
    "top_moves": [
      {
        "move": "solar-beam",
        "type": "grass",
        "power": 120,
        "score": 109.0
      },
      {
        "move": "last-resort",
        "type": "normal",
        "power": 140,
        "score": 108.0
      },
      {
        "move": "moonblast",
        "type": "fairy",
        "power": 95,
        "score": 106.5
      },
      {
        "move": "play-rough",
        "type": "fairy",
        "power": 90,
        "score": 102.0
      },
      {
        "move": "dazzling-gleam",
        "type": "fairy",
        "power": 80,
        "score": 96.0
      },
      {
        "move": "alluring-voice",
        "type": "fairy",
        "power": 80,
        "score": 96.0
      },
      {
        "move": "double-edge",
        "type": "normal",
        "power": 120,
        "score": 94.0
      }
    ]
  },
  "174": {
    "name": "igglybuff",
    "top_moves": [
      {
        "move": "last-resort",
        "type": "normal",
        "power": 140,
        "score": 138.0
      },
      {
        "move": "double-edge",
        "type": "normal",
        "power": 120,
        "score": 124.0
      },
      {
        "move": "mega-kick",
        "type": "normal",
        "power": 120,
        "score": 121.5
      },
      {
        "move": "solar-beam",
        "type": "grass",
        "power": 120,
        "score": 109.0
      },
      {
        "move": "uproar",
        "type": "normal",
        "power": 90,
        "score": 103.0
      },
      {
        "move": "hyper-voice",
        "type": "normal",
        "power": 90,
        "score": 103.0
      },
      {
        "move": "play-rough",
        "type": "fairy",
        "power": 90,
        "score": 102.0
      }
    ]
  },
  "175": {
    "name": "togepi",
    "top_moves": [
      {
        "move": "solar-beam",
        "type": "grass",
        "power": 120,
        "score": 109.0
      },
      {
        "move": "last-resort",
        "type": "normal",
        "power": 140,
        "score": 108.0
      },
      {
        "move": "moonblast",
        "type": "fairy",
        "power": 95,
        "score": 106.5
      },
      {
        "move": "play-rough",
        "type": "fairy",
        "power": 90,
        "score": 102.0
      },
      {
        "move": "dazzling-gleam",
        "type": "fairy",
        "power": 80,
        "score": 96.0
      },
      {
        "move": "double-edge",
        "type": "normal",
        "power": 120,
        "score": 94.0
      },
      {
        "move": "future-sight",
        "type": "psychic",
        "power": 120,
        "score": 94.0
      }
    ]
  },
  "176": {
    "name": "togetic",
    "top_moves": [
      {
        "move": "sky-attack",
        "type": "flying",
        "power": 140,
        "score": 152.0
      },
      {
        "move": "hyper-beam",
        "type": "normal",
        "power": 150,
        "score": 129.0
      },
      {
        "move": "giga-impact",
        "type": "normal",
        "power": 150,
        "score": 129.0
      },
      {
        "move": "focus-punch",
        "type": "fighting",
        "power": 150,
        "score": 115.0
      },
      {
        "move": "solar-beam",
        "type": "grass",
        "power": 120,
        "score": 109.0
      },
      {
        "move": "last-resort",
        "type": "normal",
        "power": 140,
        "score": 108.0
      },
      {
        "move": "moonblast",
        "type": "fairy",
        "power": 95,
        "score": 106.5
      }
    ]
  },
  "177": {
    "name": "natu",
    "top_moves": [
      {
        "move": "sky-attack",
        "type": "flying",
        "power": 140,
        "score": 152.0
      },
      {
        "move": "future-sight",
        "type": "psychic",
        "power": 120,
        "score": 124.0
      },
      {
        "move": "synchronoise",
        "type": "psychic",
        "power": 120,
        "score": 124.0
      },
      {
        "move": "dream-eater",
        "type": "psychic",
        "power": 100,
        "score": 110.0
      },
      {
        "move": "solar-beam",
        "type": "grass",
        "power": 120,
        "score": 109.0
      },
      {
        "move": "psychic",
        "type": "psychic",
        "power": 90,
        "score": 103.0
      },
      {
        "move": "drill-peck",
        "type": "flying",
        "power": 80,
        "score": 96.0
      }
    ]
  },
  "178": {
    "name": "xatu",
    "top_moves": [
      {
        "move": "sky-attack",
        "type": "flying",
        "power": 140,
        "score": 152.0
      },
      {
        "move": "hyper-beam",
        "type": "normal",
        "power": 150,
        "score": 129.0
      },
      {
        "move": "giga-impact",
        "type": "normal",
        "power": 150,
        "score": 129.0
      },
      {
        "move": "future-sight",
        "type": "psychic",
        "power": 120,
        "score": 124.0
      },
      {
        "move": "dream-eater",
        "type": "psychic",
        "power": 100,
        "score": 110.0
      },
      {
        "move": "solar-beam",
        "type": "grass",
        "power": 120,
        "score": 109.0
      },
      {
        "move": "psychic",
        "type": "psychic",
        "power": 90,
        "score": 103.0
      }
    ]
  },
  "179": {
    "name": "mareep",
    "top_moves": [
      {
        "move": "zap-cannon",
        "type": "electric",
        "power": 120,
        "score": 119.0
      },
      {
        "move": "thunder",
        "type": "electric",
        "power": 110,
        "score": 114.0
      },
      {
        "move": "thunderbolt",
        "type": "electric",
        "power": 90,
        "score": 103.0
      },
      {
        "move": "wild-charge",
        "type": "electric",
        "power": 90,
        "score": 103.0
      },
      {
        "move": "discharge",
        "type": "electric",
        "power": 80,
        "score": 96.0
      },
      {
        "move": "double-edge",
        "type": "normal",
        "power": 120,
        "score": 94.0
      },
      {
        "move": "volt-switch",
        "type": "electric",
        "power": 70,
        "score": 89.0
      }
    ]
  },
  "180": {
    "name": "flaaffy",
    "top_moves": [
      {
        "move": "zap-cannon",
        "type": "electric",
        "power": 120,
        "score": 119.0
      },
      {
        "move": "focus-punch",
        "type": "fighting",
        "power": 150,
        "score": 115.0
      },
      {
        "move": "thunder",
        "type": "electric",
        "power": 110,
        "score": 114.0
      },
      {
        "move": "thunderbolt",
        "type": "electric",
        "power": 90,
        "score": 103.0
      },
      {
        "move": "wild-charge",
        "type": "electric",
        "power": 90,
        "score": 103.0
      },
      {
        "move": "discharge",
        "type": "electric",
        "power": 80,
        "score": 96.0
      },
      {
        "move": "double-edge",
        "type": "normal",
        "power": 120,
        "score": 94.0
      }
    ]
  },
  "181": {
    "name": "ampharos",
    "top_moves": [
      {
        "move": "hyper-beam",
        "type": "normal",
        "power": 150,
        "score": 129.0
      },
      {
        "move": "giga-impact",
        "type": "normal",
        "power": 150,
        "score": 129.0
      },
      {
        "move": "zap-cannon",
        "type": "electric",
        "power": 120,
        "score": 119.0
      },
      {
        "move": "focus-punch",
        "type": "fighting",
        "power": 150,
        "score": 115.0
      },
      {
        "move": "thunder",
        "type": "electric",
        "power": 110,
        "score": 114.0
      },
      {
        "move": "supercell-slam",
        "type": "electric",
        "power": 100,
        "score": 109.5
      },
      {
        "move": "thunderbolt",
        "type": "electric",
        "power": 90,
        "score": 103.0
      }
    ]
  },
  "182": {
    "name": "bellossom",
    "top_moves": [
      {
        "move": "solar-blade",
        "type": "grass",
        "power": 125,
        "score": 142.5
      },
      {
        "move": "solar-beam",
        "type": "grass",
        "power": 120,
        "score": 139.0
      },
      {
        "move": "leaf-storm",
        "type": "grass",
        "power": 130,
        "score": 130.0
      },
      {
        "move": "hyper-beam",
        "type": "normal",
        "power": 150,
        "score": 129.0
      },
      {
        "move": "giga-impact",
        "type": "normal",
        "power": 150,
        "score": 129.0
      },
      {
        "move": "petal-dance",
        "type": "grass",
        "power": 120,
        "score": 124.0
      },
      {
        "move": "leaf-blade",
        "type": "grass",
        "power": 90,
        "score": 103.0
      }
    ]
  },
  "183": {
    "name": "marill",
    "top_moves": [
      {
        "move": "hydro-pump",
        "type": "water",
        "power": 110,
        "score": 115.0
      },
      {
        "move": "focus-punch",
        "type": "fighting",
        "power": 150,
        "score": 115.0
      },
      {
        "move": "misty-explosion",
        "type": "fairy",
        "power": 100,
        "score": 110.0
      },
      {
        "move": "surf",
        "type": "water",
        "power": 90,
        "score": 103.0
      },
      {
        "move": "aqua-tail",
        "type": "water",
        "power": 90,
        "score": 102.0
      },
      {
        "move": "play-rough",
        "type": "fairy",
        "power": 90,
        "score": 102.0
      },
      {
        "move": "muddy-water",
        "type": "water",
        "power": 90,
        "score": 101.5
      }
    ]
  },
  "184": {
    "name": "azumarill",
    "top_moves": [
      {
        "move": "hyper-beam",
        "type": "normal",
        "power": 150,
        "score": 129.0
      },
      {
        "move": "giga-impact",
        "type": "normal",
        "power": 150,
        "score": 129.0
      },
      {
        "move": "hydro-pump",
        "type": "water",
        "power": 110,
        "score": 115.0
      },
      {
        "move": "focus-punch",
        "type": "fighting",
        "power": 150,
        "score": 115.0
      },
      {
        "move": "misty-explosion",
        "type": "fairy",
        "power": 100,
        "score": 110.0
      },
      {
        "move": "surf",
        "type": "water",
        "power": 90,
        "score": 103.0
      },
      {
        "move": "aqua-tail",
        "type": "water",
        "power": 90,
        "score": 102.0
      }
    ]
  },
  "185": {
    "name": "sudowoodo",
    "top_moves": [
      {
        "move": "explosion",
        "type": "normal",
        "power": 250,
        "score": 185.0
      },
      {
        "move": "self-destruct",
        "type": "normal",
        "power": 200,
        "score": 150.0
      },
      {
        "move": "head-smash",
        "type": "rock",
        "power": 150,
        "score": 143.0
      },
      {
        "move": "hyper-beam",
        "type": "normal",
        "power": 150,
        "score": 129.0
      },
      {
        "move": "giga-impact",
        "type": "normal",
        "power": 150,
        "score": 129.0
      },
      {
        "move": "meteor-beam",
        "type": "rock",
        "power": 120,
        "score": 123.0
      },
      {
        "move": "focus-punch",
        "type": "fighting",
        "power": 150,
        "score": 115.0
      }
    ]
  },
  "186": {
    "name": "politoed",
    "top_moves": [
      {
        "move": "hyper-beam",
        "type": "normal",
        "power": 150,
        "score": 129.0
      },
      {
        "move": "giga-impact",
        "type": "normal",
        "power": 150,
        "score": 129.0
      },
      {
        "move": "hydro-pump",
        "type": "water",
        "power": 110,
        "score": 115.0
      },
      {
        "move": "focus-punch",
        "type": "fighting",
        "power": 150,
        "score": 115.0
      },
      {
        "move": "surf",
        "type": "water",
        "power": 90,
        "score": 103.0
      },
      {
        "move": "muddy-water",
        "type": "water",
        "power": 90,
        "score": 101.5
      },
      {
        "move": "liquidation",
        "type": "water",
        "power": 85,
        "score": 99.5
      }
    ]
  },
  "187": {
    "name": "hoppip",
    "top_moves": [
      {
        "move": "solar-beam",
        "type": "grass",
        "power": 120,
        "score": 139.0
      },
      {
        "move": "leaf-storm",
        "type": "grass",
        "power": 130,
        "score": 130.0
      },
      {
        "move": "energy-ball",
        "type": "grass",
        "power": 90,
        "score": 103.0
      },
      {
        "move": "bounce",
        "type": "flying",
        "power": 85,
        "score": 98.0
      },
      {
        "move": "seed-bomb",
        "type": "grass",
        "power": 80,
        "score": 96.0
      },
      {
        "move": "double-edge",
        "type": "normal",
        "power": 120,
        "score": 94.0
      },
      {
        "move": "giga-drain",
        "type": "grass",
        "power": 75,
        "score": 92.5
      }
    ]
  },
  "188": {
    "name": "skiploom",
    "top_moves": [
      {
        "move": "solar-beam",
        "type": "grass",
        "power": 120,
        "score": 139.0
      },
      {
        "move": "leaf-storm",
        "type": "grass",
        "power": 130,
        "score": 130.0
      },
      {
        "move": "energy-ball",
        "type": "grass",
        "power": 90,
        "score": 103.0
      },
      {
        "move": "bounce",
        "type": "flying",
        "power": 85,
        "score": 98.0
      },
      {
        "move": "seed-bomb",
        "type": "grass",
        "power": 80,
        "score": 96.0
      },
      {
        "move": "double-edge",
        "type": "normal",
        "power": 120,
        "score": 94.0
      },
      {
        "move": "giga-drain",
        "type": "grass",
        "power": 75,
        "score": 92.5
      }
    ]
  },
  "189": {
    "name": "jumpluff",
    "top_moves": [
      {
        "move": "solar-beam",
        "type": "grass",
        "power": 120,
        "score": 139.0
      },
      {
        "move": "leaf-storm",
        "type": "grass",
        "power": 130,
        "score": 130.0
      },
      {
        "move": "hyper-beam",
        "type": "normal",
        "power": 150,
        "score": 129.0
      },
      {
        "move": "giga-impact",
        "type": "normal",
        "power": 150,
        "score": 129.0
      },
      {
        "move": "energy-ball",
        "type": "grass",
        "power": 90,
        "score": 103.0
      },
      {
        "move": "bounce",
        "type": "flying",
        "power": 85,
        "score": 98.0
      },
      {
        "move": "seed-bomb",
        "type": "grass",
        "power": 80,
        "score": 96.0
      }
    ]
  },
  "190": {
    "name": "aipom",
    "top_moves": [
      {
        "move": "last-resort",
        "type": "normal",
        "power": 140,
        "score": 138.0
      },
      {
        "move": "double-edge",
        "type": "normal",
        "power": 120,
        "score": 124.0
      },
      {
        "move": "mega-kick",
        "type": "normal",
        "power": 120,
        "score": 121.5
      },
      {
        "move": "focus-punch",
        "type": "fighting",
        "power": 150,
        "score": 115.0
      },
      {
        "move": "solar-beam",
        "type": "grass",
        "power": 120,
        "score": 109.0
      },
      {
        "move": "uproar",
        "type": "normal",
        "power": 90,
        "score": 103.0
      },
      {
        "move": "take-down",
        "type": "normal",
        "power": 90,
        "score": 101.5
      }
    ]
  },
  "191": {
    "name": "sunkern",
    "top_moves": [
      {
        "move": "solar-beam",
        "type": "grass",
        "power": 120,
        "score": 139.0
      },
      {
        "move": "leaf-storm",
        "type": "grass",
        "power": 130,
        "score": 130.0
      },
      {
        "move": "energy-ball",
        "type": "grass",
        "power": 90,
        "score": 103.0
      },
      {
        "move": "seed-bomb",
        "type": "grass",
        "power": 80,
        "score": 96.0
      },
      {
        "move": "double-edge",
        "type": "normal",
        "power": 120,
        "score": 94.0
      },
      {
        "move": "giga-drain",
        "type": "grass",
        "power": 75,
        "score": 92.5
      },
      {
        "move": "razor-leaf",
        "type": "grass",
        "power": 55,
        "score": 78.0
      }
    ]
  },
  "192": {
    "name": "sunflora",
    "top_moves": [
      {
        "move": "solar-beam",
        "type": "grass",
        "power": 120,
        "score": 139.0
      },
      {
        "move": "leaf-storm",
        "type": "grass",
        "power": 130,
        "score": 130.0
      },
      {
        "move": "hyper-beam",
        "type": "normal",
        "power": 150,
        "score": 129.0
      },
      {
        "move": "giga-impact",
        "type": "normal",
        "power": 150,
        "score": 129.0
      },
      {
        "move": "petal-dance",
        "type": "grass",
        "power": 120,
        "score": 124.0
      },
      {
        "move": "energy-ball",
        "type": "grass",
        "power": 90,
        "score": 103.0
      },
      {
        "move": "petal-blizzard",
        "type": "grass",
        "power": 90,
        "score": 103.0
      }
    ]
  },
  "193": {
    "name": "yanma",
    "top_moves": [
      {
        "move": "solar-beam",
        "type": "grass",
        "power": 120,
        "score": 109.0
      },
      {
        "move": "bug-buzz",
        "type": "bug",
        "power": 90,
        "score": 103.0
      },
      {
        "move": "leech-life",
        "type": "bug",
        "power": 80,
        "score": 96.0
      },
      {
        "move": "lunge",
        "type": "bug",
        "power": 80,
        "score": 96.0
      },
      {
        "move": "double-edge",
        "type": "normal",
        "power": 120,
        "score": 94.0
      },
      {
        "move": "signal-beam",
        "type": "bug",
        "power": 75,
        "score": 92.5
      },
      {
        "move": "air-slash",
        "type": "flying",
        "power": 75,
        "score": 92.0
      }
    ]
  },
  "194": {
    "name": "wooper",
    "top_moves": [
      {
        "move": "hydro-pump",
        "type": "water",
        "power": 110,
        "score": 115.0
      },
      {
        "move": "earthquake",
        "type": "ground",
        "power": 100,
        "score": 110.0
      },
      {
        "move": "surf",
        "type": "water",
        "power": 90,
        "score": 103.0
      },
      {
        "move": "earth-power",
        "type": "ground",
        "power": 90,
        "score": 103.0
      },
      {
        "move": "aqua-tail",
        "type": "water",
        "power": 90,
        "score": 102.0
      },
      {
        "move": "muddy-water",
        "type": "water",
        "power": 90,
        "score": 101.5
      },
      {
        "move": "liquidation",
        "type": "water",
        "power": 85,
        "score": 99.5
      }
    ]
  },
  "195": {
    "name": "quagsire",
    "top_moves": [
      {
        "move": "hyper-beam",
        "type": "normal",
        "power": 150,
        "score": 129.0
      },
      {
        "move": "giga-impact",
        "type": "normal",
        "power": 150,
        "score": 129.0
      },
      {
        "move": "hydro-pump",
        "type": "water",
        "power": 110,
        "score": 115.0
      },
      {
        "move": "focus-punch",
        "type": "fighting",
        "power": 150,
        "score": 115.0
      },
      {
        "move": "earthquake",
        "type": "ground",
        "power": 100,
        "score": 110.0
      },
      {
        "move": "high-horsepower",
        "type": "ground",
        "power": 95,
        "score": 106.0
      },
      {
        "move": "surf",
        "type": "water",
        "power": 90,
        "score": 103.0
      }
    ]
  },
  "196": {
    "name": "espeon",
    "top_moves": [
      {
        "move": "hyper-beam",
        "type": "normal",
        "power": 150,
        "score": 129.0
      },
      {
        "move": "giga-impact",
        "type": "normal",
        "power": 150,
        "score": 129.0
      },
      {
        "move": "future-sight",
        "type": "psychic",
        "power": 120,
        "score": 124.0
      },
      {
        "move": "dream-eater",
        "type": "psychic",
        "power": 100,
        "score": 110.0
      },
      {
        "move": "last-resort",
        "type": "normal",
        "power": 140,
        "score": 108.0
      },
      {
        "move": "psychic",
        "type": "psychic",
        "power": 90,
        "score": 103.0
      },
      {
        "move": "psychic-fangs",
        "type": "psychic",
        "power": 85,
        "score": 99.5
      }
    ]
  },
  "197": {
    "name": "umbreon",
    "top_moves": [
      {
        "move": "hyper-beam",
        "type": "normal",
        "power": 150,
        "score": 129.0
      },
      {
        "move": "giga-impact",
        "type": "normal",
        "power": 150,
        "score": 129.0
      },
      {
        "move": "last-resort",
        "type": "normal",
        "power": 140,
        "score": 108.0
      },
      {
        "move": "foul-play",
        "type": "dark",
        "power": 95,
        "score": 106.5
      },
      {
        "move": "sucker-punch",
        "type": "dark",
        "power": 70,
        "score": 99.0
      },
      {
        "move": "crunch",
        "type": "dark",
        "power": 80,
        "score": 96.0
      },
      {
        "move": "dark-pulse",
        "type": "dark",
        "power": 80,
        "score": 96.0
      }
    ]
  },
  "198": {
    "name": "murkrow",
    "top_moves": [
      {
        "move": "sky-attack",
        "type": "flying",
        "power": 140,
        "score": 152.0
      },
      {
        "move": "hyper-beam",
        "type": "normal",
        "power": 150,
        "score": 129.0
      },
      {
        "move": "giga-impact",
        "type": "normal",
        "power": 150,
        "score": 129.0
      },
      {
        "move": "brave-bird",
        "type": "flying",
        "power": 120,
        "score": 124.0
      },
      {
        "move": "hurricane",
        "type": "flying",
        "power": 110,
        "score": 114.0
      },
      {
        "move": "foul-play",
        "type": "dark",
        "power": 95,
        "score": 106.5
      },
      {
        "move": "fly",
        "type": "flying",
        "power": 90,
        "score": 102.5
      }
    ]
  },
  "199": {
    "name": "slowking",
    "top_moves": [
      {
        "move": "hyper-beam",
        "type": "normal",
        "power": 150,
        "score": 129.0
      },
      {
        "move": "giga-impact",
        "type": "normal",
        "power": 150,
        "score": 129.0
      },
      {
        "move": "future-sight",
        "type": "psychic",
        "power": 120,
        "score": 124.0
      },
      {
        "move": "hydro-pump",
        "type": "water",
        "power": 110,
        "score": 115.0
      },
      {
        "move": "focus-punch",
        "type": "fighting",
        "power": 150,
        "score": 115.0
      },
      {
        "move": "dream-eater",
        "type": "psychic",
        "power": 100,
        "score": 110.0
      },
      {
        "move": "surf",
        "type": "water",
        "power": 90,
        "score": 103.0
      }
    ]
  },
  "200": {
    "name": "misdreavus",
    "top_moves": [
      {
        "move": "hyper-beam",
        "type": "normal",
        "power": 150,
        "score": 129.0
      },
      {
        "move": "giga-impact",
        "type": "normal",
        "power": 150,
        "score": 129.0
      },
      {
        "move": "poltergeist",
        "type": "ghost",
        "power": 110,
        "score": 116.0
      },
      {
        "move": "phantom-force",
        "type": "ghost",
        "power": 90,
        "score": 103.0
      },
      {
        "move": "shadow-ball",
        "type": "ghost",
        "power": 80,
        "score": 96.0
      },
      {
        "move": "double-edge",
        "type": "normal",
        "power": 120,
        "score": 94.0
      },
      {
        "move": "future-sight",
        "type": "psychic",
        "power": 120,
        "score": 94.0
      }
    ]
  },
  "201": {
    "name": "unown",
    "top_moves": [
      {
        "move": "hidden-power",
        "type": "normal",
        "power": 60,
        "score": 52.0
      }
    ]
  },
  "202": {
    "name": "wobbuffet",
    "top_moves": [
      {
        "move": "mirror-coat",
        "type": "psychic",
        "power": null,
        "score": 40.0
      }
    ]
  },
  "203": {
    "name": "girafarig",
    "top_moves": [
      {
        "move": "hyper-beam",
        "type": "normal",
        "power": 150,
        "score": 159.0
      },
      {
        "move": "giga-impact",
        "type": "normal",
        "power": 150,
        "score": 159.0
      },
      {
        "move": "double-edge",
        "type": "normal",
        "power": 120,
        "score": 124.0
      },
      {
        "move": "future-sight",
        "type": "psychic",
        "power": 120,
        "score": 124.0
      },
      {
        "move": "razor-wind",
        "type": "normal",
        "power": 80,
        "score": 111.0
      },
      {
        "move": "dream-eater",
        "type": "psychic",
        "power": 100,
        "score": 110.0
      },
      {
        "move": "psychic",
        "type": "psychic",
        "power": 90,
        "score": 103.0
      }
    ]
  },
  "204": {
    "name": "pineco",
    "top_moves": [
      {
        "move": "explosion",
        "type": "normal",
        "power": 250,
        "score": 185.0
      },
      {
        "move": "self-destruct",
        "type": "normal",
        "power": 200,
        "score": 150.0
      },
      {
        "move": "solar-beam",
        "type": "grass",
        "power": 120,
        "score": 109.0
      },
      {
        "move": "bug-buzz",
        "type": "bug",
        "power": 90,
        "score": 103.0
      },
      {
        "move": "lunge",
        "type": "bug",
        "power": 80,
        "score": 96.0
      },
      {
        "move": "double-edge",
        "type": "normal",
        "power": 120,
        "score": 94.0
      },
      {
        "move": "bug-bite",
        "type": "bug",
        "power": 60,
        "score": 82.0
      }
    ]
  },
  "205": {
    "name": "forretress",
    "top_moves": [
      {
        "move": "explosion",
        "type": "normal",
        "power": 250,
        "score": 185.0
      },
      {
        "move": "self-destruct",
        "type": "normal",
        "power": 200,
        "score": 150.0
      },
      {
        "move": "steel-beam",
        "type": "steel",
        "power": 140,
        "score": 137.5
      },
      {
        "move": "hyper-beam",
        "type": "normal",
        "power": 150,
        "score": 129.0
      },
      {
        "move": "giga-impact",
        "type": "normal",
        "power": 150,
        "score": 129.0
      },
      {
        "move": "solar-beam",
        "type": "grass",
        "power": 120,
        "score": 109.0
      },
      {
        "move": "bug-buzz",
        "type": "bug",
        "power": 90,
        "score": 103.0
      }
    ]
  }
}